odoo/addons/sm_rewards_emc/__init__.py
odoo/addons/sm_rewards_emc/__manifest__.py
odoo/addons/sm_rewards_emc/models/__init__.py
odoo/addons/sm_rewards_emc/models/models_sm_reward.py
odoo/addons/sm_rewards_emc/models/models_subscription_request.py
odoo/addons/sm_rewards_emc/views/views_reward.xml
odoo/addons/sm_rewards_emc/views/views_subscription_request.xml
odoo12_addon_sm_rewards_emc-12.0.0.0.3.dist-info/METADATA
odoo12_addon_sm_rewards_emc-12.0.0.0.3.dist-info/WHEEL
odoo12_addon_sm_rewards_emc-12.0.0.0.3.dist-info/top_level.txt
odoo12_addon_sm_rewards_emc-12.0.0.0.3.dist-info/RECORD
