Metadata-Version: 2.1
Name: odoo12-addon-sm-rewards-emc
Version: 12.0.0.0.3
Summary: sm_rewards_emc
Home-page: http://www.sommobilitat.coop
Author: Som Mobilitat
Classifier: Programming Language :: Python
Classifier: Framework :: Odoo
Classifier: Framework :: Odoo :: 12.0
Requires-Python: >=3.5
Requires-Dist: odoo12-addon-easy-my-coop
Requires-Dist: odoo12-addon-sm-rewards
Requires-Dist: odoo (<12.1dev,>=12.0a)
